{
  "update_date_nh1": "2023-12-26 21:52:12",
  "buyable_cash_dollar_nh1": 790.6607153888923,
  "portfolio_dict_nh1": {
    "TLT": [
      "BOND",
      "NASD",
      98.66,
      310,
      30584.6,
      39.56180151290043,
      40,
      314,
      30979.239999999998,
      40.0722763711314,
      40,
      4,
      394.64,
      0.0722763711314002,
      98.65,
      98.66
    ],
    "BRK/B": [
      "STOCK",
      "NYSE",
      356.8,
      43,
      15342.4,
      19.84570612437382,
      20,
      43,
      15342.4,
      19.84570612437382,
      20,
      0,
      0.0,
      -0.1543,
      356.6,
      356.8
    ],
    "XLU": [
      "STOCK",
      "AMEX",
      62.62,
      120,
      7514.4,
      9.720029076350157,
      10,
      126,
      7890.12,
      10.206030530167663,
      10,
      6,
      375.71999999999997,
      0.20603053016766387,
      56.61,
      68.63
    ],
    "AMZN": [
      "STOCK",
      "NASD",
      153.99,
      50,
      7699.5,
      9.959459687181681,
      10,
      50,
      7699.5,
      9.959459687181681,
      10,
      0,
      0.0,
      -0.0405,
      153.99,
      154.0
    ],
    "GOOG": [
      "STOCK",
      "NASD",
      143.07,
      55,
      7868.849999999999,
      10.178517353007283,
      10,
      55,
      7868.849999999999,
      10.178517353007283,
      10,
      0,
      0.0,
      0.1785,
      142.96,
      143.05
    ],
    "MSFT": [
      "STOCK",
      "NASD",
      375.4,
      20,
      7508.0,
      9.711750546316003,
      10,
      20,
      7508.0,
      9.711750546316003,
      10,
      0,
      0.0,
      -0.2882,
      375.3,
      375.4
    ]
  }
}